{
    "configurations": [
        {
            "name": "Win32",
            "includePath": [
                "${workspaceFolder}/**",
                "${workspaceFolder}/build/config/",
                "C:\\Espressif\\frameworks\\esp-idf\\components/**",
                "C:/Espressif/frameworks/esp-idf/components/linux/include",
                "C:/Espressif/frameworks/esp-idf/components/mqtt/esp-mqtt/host_test/mocks/include"
            ],
            "defines": [
                "_DEBUG",
                "UNICODE",
                "_UNICODE"
            ],
            "windowsSdkVersion": "10.0.22000.0",
            "compilerPath": "cl.exe",
            "cStandard": "c17",
            "cppStandard": "c++17",
            "intelliSenseMode": "windows-msvc-x64"
        }
    ],
    "version": 4
}